dukatools/__init__.py
dukatools/dirproc.py
dukatools/pydown.py
dukatools/treex.py
dukatools/vidcut.py
dukatools-0.3.0.dist-info/METADATA
dukatools-0.3.0.dist-info/WHEEL
dukatools-0.3.0.dist-info/entry_points.txt
dukatools-0.3.0.dist-info/licenses/LICENSE
dukatools-0.3.0.dist-info/RECORD
