Metadata-Version: 2.4
Name: dukatools
Version: 0.3.0
Summary: Small cross-platform CLI toolbelt: treex, dirproc, and more.
License-Expression: MIT
License-File: LICENSE
Keywords: cli,utilities,filesystem,tree
Author: rexologue
Requires-Python: >=3.10
Classifier: Programming Language :: Python :: 3
Classifier: License :: OSI Approved :: MIT License
Classifier: Operating System :: OS Independent
Requires-Dist: chardet (>=5,<6)
Requires-Dist: imageio-ffmpeg (>=0.4)
Project-URL: Bug Tracker, https://github.com/rexologue/dukatools/issues
Project-URL: Homepage, https://github.com/rexologue/dukatools
Project-URL: Repository, https://github.com/rexologue/dukatools
